[
   {
      "id":0,
      "name":"Atlantic Radio",
      "propellant":"http://atlanticradio.ma:8000/stream/1/",
      "imageurl":"https://cdn.webrad.io/images/logos/radio-co-ma/atlantic.png"
   },
   {
      "id":1,
      "name":"Izlanzik Radio",
      "propellant":"http://server.izlanzik.org:8000/stream/1/",
      "imageurl":"https://cdn.webrad.io/images/logos/radio-co-ma/izlanzik.png"
   },
   {
      "id":2,
      "name":"NRJ Maroc",
      "propellant":"https://scdn.nrjaudio.fm/adwz1/ma/55820/mp3_128.mp3?origine=radio",
      "imageurl":"https://cdn.webrad.io/images/logos/radio-co-ma/nrj-maroc.png"
   },
   {
      "id":3,
      "name":"Medi 1",
      "propellant":"https://live.medi1.com/medi1",
      "imageurl":"https://cdn.webrad.io/images/logos/radio-co-ma/medi.png"
   },
   {
      "id":4,
      "name":"Izlan",
      "propellant":"http://51.15.191.112:8181/stream/1/",
      "imageurl":"https://cdn.webrad.io/images/logos/radio-co-ma/izlan.png"
   },
   {
      "id":5,
      "name":"Anwa-rock",
      "propellant":"https://streamingv2.shoutcast.com/Anwa-rock",
      "imageurl":"https://cdn.webrad.io/images/logos/radio-co-ma/anwa-rock.png"
   },
   {
      "id":6,
      "name":"The Moroccan Radio",
      "propellant":"https://streamingv2.shoutcast.com/TheMoroccanRadio",
      "imageurl":"https://cdn.webrad.io/images/logos/radio-co-ma/moroccan.png"
   },
   {
      "id":7,
      "name":"Radio Sawt (Ouarzazate)",
      "propellant":"http://109.169.15.20:7366/;",
      "imageurl":"https://cdn.webrad.io/images/logos/radio-co-ma/sawt-ouarzazate.png"
   },
   {
      "id":8,
      "name":"MFM Radio",
      "propellant":"https://streamer.eagrpservices.com/audio/mfmradio.ogg",
      "imageurl":"https://cdn.webrad.io/images/logos/radio-co-ma/mfm.png"
   },
   {
      "id":9,
      "name":"Med Radio",
      "propellant":"https://medradio-maroc.ice.infomaniak.ch/medradio-maroc-64.mp3",
      "imageurl":"https://cdn.webrad.io/images/logos/radio-co-ma/med.png"
   },
   {
      "id":10,
      "name":"Hit Radio Mgharba",
      "propellant":"https://mgharba.ice.infomaniak.ch/mgharba-128.mp3",
      "imageurl":"https://cdn.webrad.io/images/logos/radio-co-ma/hit-mgharba.png"
   },
   {
      "id":12,
      "name":"Cap Radio",
      "propellant":"https://eu8.fastcast4u.com/proxy/caprad00?mp=/stream/1/",
      "imageurl":"https://cdn.webrad.io/images/logos/radio-co-ma/cap.png"
   },
   {
      "id":14,
      "name":"Ness Radio",
      "propellant":"http://radio.nessradio.net:8000/nessradio.mp3",
      "imageurl":"https://cdn.webrad.io/images/logos/radio-co-ma/ness.png"
   },
   {
      "id":16,
      "name":"Radio Atbir",
      "propellant":"https://stream.zenolive.com/bqdbb6hd0neuv",
      "imageurl":"https://cdn.webrad.io/images/logos/radio-co-ma/atbir.png"
   },
   {
      "id":17,
      "name":"Radio Yabiladi",
      "propellant":"http://snassen.yabiladi.com:8000/stream/1/",
      "imageurl":"https://cdn.webrad.io/images/logos/radio-co-ma/yabiladi.png"
   },
   {
      "id":18,
      "name":"Radio Monte Carlo Doualiya",
      "propellant":"https://montecarlodoualiya128k.ice.infomaniak.ch/mc-doualiya.mp3",
      "imageurl":"https://cdn.webrad.io/images/logos/radio-co-ma/monte-calro-doualiya.png"
   },
   {
      "id":20,
      "name":"Radio Anwarock",
      "propellant":"https://streamingv2.shoutcast.com/Anwa-rock",
      "imageurl":"https://cdn.webrad.io/images/logos/radio-co-ma/anwarock.png"
   },
   {
      "id":23,
      "name":"Radio Soleil",
      "propellant":"https://radiosoleil.ice.infomaniak.ch/radiosoleil-96.mp3",
      "imageurl":"https://cdn.webrad.io/images/logos/radio-co-ma/soleil.png"
   },
   {
      "id":24,
      "name":"Radio Medina FM",
      "propellant":"https://medinafm.ice.infomaniak.ch/medinafm-64.mp3",
      "imageurl":"https://cdn.webrad.io/images/logos/radio-co-ma/medina.png"
   },
   {
      "id":25,
      "name":"Radio Sawa",
      "propellant":"https://stream.radiojar.com/1w27tnzst5quv",
      "imageurl":"https://cdn.webrad.io/images/logos/radio-co-ma/sawa.png"
   },
   {
      "id":26,
      "name":"Hit Radio French",
      "propellant":"https://french.ice.infomaniak.ch/french-128.mp3",
      "imageurl":"https://cdn.webrad.io/images/logos/radio-co-ma/french.png"
   },
   {
      "id":27,
      "name":"Chada FM",
      "propellant":"https://live-reflector.ice.infomaniak.ch/chadafm-high.mp3",
      "imageurl":"https://cdn.webrad.io/images/logos/radio-co-ma/chada.png"
   },
   {
      "id":28,
      "name":"Radio Coran",
      "propellant":"http://92.222.103.13:8005/stream/1/",
      "imageurl":"https://cdn.webrad.io/images/logos/radio-co-ma/coran.png"
   },
   {
      "id":29,
      "name":"Hit Radio RnB",
      "propellant":"https://rnb.ice.infomaniak.ch/rnb-128.mp3",
      "imageurl":"https://cdn.webrad.io/images/logos/radio-co-ma/hit-rnb.png"
   },
   {
      "id":30,
      "name":"Orient FM",
      "propellant":"https://stream-broadcast.ovh/Radio-Orient.mp3",
      "imageurl":"https://cdn.webrad.io/images/logos/radio-co-ma/orient-fm.png"
   },
   {
      "id":31,
      "name":"Aswat",
      "propellant":"https://broadcast.ice.infomaniak.ch/aswat-high.mp3",
      "imageurl":"https://cdn.webrad.io/images/logos/radio-co-ma/aswat.png"
   },
   {
      "id":33,
      "name":"Hit Radio Dancefloor",
      "propellant":"https://dancefloor.ice.infomaniak.ch/dancefloor-128.mp3",
      "imageurl":"https://cdn.webrad.io/images/logos/radio-co-ma/hit-radio-dancefloor.png"
   },
   {
      "id":34,
      "name":"Hit Radio Rock/Metal",
      "propellant":"https://rockmetal.ice.infomaniak.ch/rockmetal-128.mp3",
      "imageurl":"https://cdn.webrad.io/images/logos/radio-co-ma/rock-metal.png"
   },
   {
      "id":35,
      "name":"Radio Star Maroc FM",
      "propellant":"https://streamingv2.shoutcast.com/RadioStarMaroc",
      "imageurl":"https://cdn.webrad.io/images/logos/radio-co-ma/star-maroc.png"
   },
   {
      "id":37,
      "name":"Hit Radio Gold",
      "propellant":"https://gold.ice.infomaniak.ch/gold-128.mp3",
      "imageurl":"https://cdn.webrad.io/images/logos/radio-co-ma/hit-radio-gold.png"
   },
   {
      "id":38,
      "name":"Ohayō Otaku Desu",
      "propellant":"https://stream.mixfeever.com/",
      "imageurl":"https://cdn.webrad.io/images/logos/radio-co-ma/ohayo.png"
   },
   {
      "id":39,
      "name":"4U Classic Rock",
      "propellant":"https://str4uice.streamakaci.com/4uclassicrock.mp3",
      "imageurl":"https://cdn.webrad.io/images/logos/radio-co-ma/4u-classic.png"
   },
   {
      "id":40,
      "name":"Radio Mars",
      "propellant":"https://radiomars.ice.infomaniak.ch/radiomars-128.mp3",
      "imageurl":"https://cdn.webrad.io/images/logos/radio-co-ma/mars.png"
   },
   {
      "id":43,
      "name":"Hit Radio",
      "propellant":"https://hitradio-maroc.ice.infomaniak.ch/hitradio-maroc-128.mp3",
      "imageurl":"https://cdn.webrad.io/images/logos/radio-co-ma/hit.png"
   }
]
